odoo/addons/product_multi_company/README.rst
odoo/addons/product_multi_company/__init__.py
odoo/addons/product_multi_company/__manifest__.py
odoo/addons/product_multi_company/hooks.py
odoo/addons/product_multi_company/i18n/es.po
odoo/addons/product_multi_company/i18n/fr.po
odoo/addons/product_multi_company/i18n/hr.po
odoo/addons/product_multi_company/i18n/nl_NL.po
odoo/addons/product_multi_company/i18n/product_multi_company.pot
odoo/addons/product_multi_company/i18n/pt.po
odoo/addons/product_multi_company/migrations/13.0.1.0.0/pre-migration.py
odoo/addons/product_multi_company/migrations/13.0.2.0.0/post-migration.py
odoo/addons/product_multi_company/models/__init__.py
odoo/addons/product_multi_company/models/product_category.py
odoo/addons/product_multi_company/models/product_product.py
odoo/addons/product_multi_company/models/product_template.py
odoo/addons/product_multi_company/readme/CONTRIBUTORS.rst
odoo/addons/product_multi_company/readme/DESCRIPTION.rst
odoo/addons/product_multi_company/readme/INSTALL.rst
odoo/addons/product_multi_company/readme/USAGE.rst
odoo/addons/product_multi_company/security/product_multi_company_security.xml
odoo/addons/product_multi_company/static/description/icon.png
odoo/addons/product_multi_company/static/description/index.html
odoo/addons/product_multi_company/tests/__init__.py
odoo/addons/product_multi_company/tests/test_product_multi_company.py
odoo/addons/product_multi_company/views/product_template_view.xml
odoo13_addon_product_multi_company-13.0.2.0.1.dist-info/METADATA
odoo13_addon_product_multi_company-13.0.2.0.1.dist-info/WHEEL
odoo13_addon_product_multi_company-13.0.2.0.1.dist-info/top_level.txt
odoo13_addon_product_multi_company-13.0.2.0.1.dist-info/RECORD
