Metadata-Version: 2.1
Name: odoo13-addon-product-multi-company
Version: 13.0.2.0.1
Summary: Select individually the product template visibility on each company
Home-page: https://github.com/OCA/multi-company
Author: Tecnativa,Odoo Community Association (OCA)
Author-email: support@odoo-community.org
License: AGPL-3
Platform: UNKNOWN
Classifier: Programming Language :: Python
Classifier: Framework :: Odoo
Classifier: License :: OSI Approved :: GNU Affero General Public License v3
Requires-Python: >=3.5
Requires-Dist: odoo13-addon-base-multi-company
Requires-Dist: odoo (<13.1dev,>=13.0a)
